concertina_helper/__init__.py
concertina_helper/cli.py
concertina_helper/finger_finder.py
concertina_helper/note_generators.py
concertina_helper/notes_on_layout.py
concertina_helper/output_utils.py
concertina_helper/penalties.py
concertina_helper/py.typed
concertina_helper/type_defs.py
concertina_helper/layouts/20_cg.yaml
concertina_helper/layouts/30_jefferies_cg.yaml
concertina_helper/layouts/30_wheatstone_cg.yaml
concertina_helper/layouts/__init__.py
concertina_helper/layouts/base_classes.py
concertina_helper/layouts/bisonoric.py
concertina_helper/layouts/layout_loader.py
concertina_helper/layouts/unisonoric.py
concertina_helper-0.0.3.dist-info/entry_points.txt
concertina_helper-0.0.3.dist-info/LICENSE
concertina_helper-0.0.3.dist-info/WHEEL
concertina_helper-0.0.3.dist-info/METADATA
concertina_helper-0.0.3.dist-info/RECORD
