Metadata-Version: 2.1
Name: concertina_helper
Version: 0.0.3
Summary: Script and supporting API to find good fingerings on bisonoric concertinas
Author-email: Chuck McCallum <mccallucc@gmail.com>
Requires-Python: ~=3.10
Classifier: License :: OSI Approved :: MIT License
Requires-Dist: pyabc2==0.1.0.dev2
Requires-Dist: astar==0.97
Requires-Dist: pyyaml~=6.0
Project-URL: Home, https://github.com/mccalluc/concertina-helper
